{"controllerWindows":[{"listRules":0.0,"factoryRules":[{},{},{},{},{},{},{},{}],"toggleActive":true},{"listRules":1.0,"factoryRules":[{},{},{},{},{},{},{},{}],"toggleActive":true},{"listRules":2.0,"factoryRules":[{},{},{},{},{},{},{},{}],"toggleActive":true},{"listRules":0.0,"factoryRules":[{},{},{},{},{},{},{},{}],"toggleActive":false},{"listRules":0.0,"factoryRules":[{},{},{},{},{},{},{},{}],"toggleActive":false},{"listRules":0.0,"factoryRules":[{},{},{},{},{},{},{},{}],"toggleActive":false},{"listRules":0.0,"factoryRules":[{},{},{},{},{},{},{},{}],"toggleActive":false},{"listRules":0.0,"factoryRules":[{},{},{},{},{},{},{},{}],"toggleActive":false},{"listRules":0.0,"factoryRules":[{},{},{},{},{},{},{},{}],"toggleActive":false},{"listRules":0.0,"factoryRules":[{},{},{},{},{},{},{},{}],"toggleActive":false}],"radioSelect":2.0}